api_profiler/__init__.py
api_profiler/main.py
api_profiler/patch_settings.py
api_profiler/cache/__init__.py
api_profiler/cache/cache_keys.py
api_profiler/cache/cache_service.py
api_profiler/django_utils/__init__.py
api_profiler/django_utils/discover_app.py
api_profiler/logging/__init__.py
api_profiler/logging/log_sql.py
api_profiler/logging/logger.py
api_profiler/middleware/__init__.py
api_profiler/middleware/profiler.py
api_profiler-0.1.7.dist-info/licenses/LICENSE
api_profiler-0.1.7.dist-info/METADATA
api_profiler-0.1.7.dist-info/WHEEL
api_profiler-0.1.7.dist-info/entry_points.txt
api_profiler-0.1.7.dist-info/top_level.txt
api_profiler-0.1.7.dist-info/RECORD
