Metadata-Version: 2.4
Name: api_profiler
Version: 0.1.7
Summary: Django profiling middleware CLI tool
Home-page: https://github.com/Av-sek/api-profiler
Author: Abhishek Ghorashainee
Author-email: abhishekghorashainee07@gmail.com
License: MIT
Project-URL: Source, https://github.com/Av-sek/api-profiler
Project-URL: Tracker, https://github.com/Av-sek/api-profiler/issues
Keywords: django profiler middleware cli development
Classifier: Programming Language :: Python :: 3
Classifier: Framework :: Django
Classifier: License :: OSI Approved :: MIT License
Classifier: Operating System :: OS Independent
Classifier: Intended Audience :: Developers
Classifier: Topic :: Software Development :: Libraries :: Application Frameworks
Requires-Python: >=3.7
License-File: LICENSE
Requires-Dist: Django>=3.0
Requires-Dist: diskcache
Dynamic: author
Dynamic: author-email
Dynamic: classifier
Dynamic: description
Dynamic: description-content-type
Dynamic: home-page
Dynamic: keywords
Dynamic: license
Dynamic: license-file
Dynamic: project-url
Dynamic: requires-dist
Dynamic: requires-python
Dynamic: summary
